{
  "code": "10000",
  "data": {
    "stationDataList": [
      {
        "stationCode": 73,
        "normalNum": "12",
        "regionName": "安徽",
        "latitude": "31.730000000000",
        "alarmNum": "1",
        "yearPower": "41069829",
        "instantaneous": "8.984615384615383",
        "dayPower": "321869",
        "yearPlanPower": "48000000.0000",
        "stationPlanPower": "21906.633395185014",
        "stationStatus": {
          "stationStatus": "400",
          "stationStatusName": "通讯正常"
        },
        "standbyNum": "0",
        "stationName": "肥西风电场",
        "stationCapacity": "26",
        "longitude": "116.830000000000",
        "interruptNum": "0",
        "maintainNum": "0",
        "dayResources": "8.984615",
        "errorNum": "1",
        "shutdownNum": "0",
        "capabilityRate": "102.124318220969871276",
        "stationPower": "22372",
        "equivalentHours": "13.37957692307692307692",
        "stationUnitCount": "13",
        "provinceName": "安徽省",
        "monthPower": "3064057",
        "noAccessNum": "0",
        "yearPlanRate": "85.56214375"
      },
      {
        "stationCode": 78,
        "normalNum": "16",
        "regionName": "云南",
        "latitude": "25.870000000000",
        "alarmNum": "0",
        "yearPower": "85025445",
        "instantaneous": "13.506249999999998",
        "dayPower": "407918",
        "yearPlanPower": "97000000.0000",
        "stationPlanPower": "30998.15557365506",
        "stationStatus": {
          "stationStatus": "400",
          "stationStatusName": "通讯正常"
        },
        "standbyNum": "0",
        "stationName": "会泽白泥井",
        "stationCapacity": "32",
        "longitude": "103.330000000000",
        "interruptNum": "0",
        "maintainNum": "0",
        "dayResources": "13.50625",
        "errorNum": "0",
        "shutdownNum": "0",
        "capabilityRate": "97.955828139034182246",
        "stationPower": "30364.499999999996",
        "equivalentHours": "8.03306896551724137931",
        "stationUnitCount": "16",
        "provinceName": "云南省",
        "monthPower": "4137502",
        "noAccessNum": "0",
        "yearPlanRate": "87.655097938144329897"
      },
      {
        "stationCode": 75,
        "normalNum": "23",
        "regionName": "云南",
        "latitude": "26.070000000000",
        "alarmNum": "0",
        "yearPower": "100298402.07",
        "instantaneous": "12.481250000000001",
        "dayPower": "431560.07",
        "yearPlanPower": "117000000.0000",
        "stationPlanPower": "32089.644072271327",
        "stationStatus": {
          "stationStatus": "400",
          "stationStatusName": "通讯正常"
        },
        "standbyNum": "0",
        "stationName": "会泽仓房",
        "stationCapacity": "48",
        "longitude": "103.310000000000",
        "interruptNum": "0",
        "maintainNum": "0",
        "dayResources": "12.48125",
        "errorNum": "0",
        "shutdownNum": "1",
        "capabilityRate": "88.408584202760064944",
        "stationPower": "28370",
        "equivalentHours": "5.07132141509433962264",
        "stationUnitCount": "24",
        "provinceName": "云南省",
        "monthPower": "4603784.07",
        "noAccessNum": "0",
        "yearPlanRate": "85.725129974358974359"
      },
      {
        "stationCode": 60,
        "normalNum": "23",
        "regionName": "湖南",
        "latitude": "25.260000000000",
        "alarmNum": "52",
        "yearPower": "102717432",
        "instantaneous": "10.487499999999999",
        "dayPower": "588278",
        "yearPlanPower": "118000000.0000",
        "stationPlanPower": "41635.81779500381",
        "stationStatus": {
          "stationStatus": "400",
          "stationStatusName": "通讯正常"
        },
        "standbyNum": "0",
        "stationName": "江华界牌",
        "stationCapacity": "48",
        "longitude": "111.600000000000",
        "interruptNum": "0",
        "maintainNum": "1",
        "dayResources": "10.4875",
        "errorNum": "0",
        "shutdownNum": "0",
        "capabilityRate": "100.286249223164031511",
        "stationPower": "41755",
        "equivalentHours": "4.81998701298701298701",
        "stationUnitCount": "24",
        "provinceName": "湖南省",
        "monthPower": "7122596",
        "noAccessNum": "0",
        "yearPlanRate": "87.048671186440677966"
      },
      {
        "stationCode": 82,
        "normalNum": "0",
        "regionName": "河南",
        "latitude": "34.510000000000",
        "alarmNum": "0",
        "yearPower": "59862503.72975277782",
        "instantaneous": null,
        "dayPower": "155864.37815277782",
        "yearPlanPower": "28000000.0000",
        "stationPlanPower": "15.06264182276507241",
        "stationStatus": {
          "stationStatus": "500",
          "stationStatusName": "通讯中断"
        },
        "standbyNum": "0",
        "stationName": "灵宝杨家湾",
        "stationCapacity": "48",
        "longitude": "110.490000000000",
        "interruptNum": "24",
        "maintainNum": "0",
        "dayResources": null,
        "errorNum": "0",
        "shutdownNum": "0",
        "capabilityRate": null,
        "stationPower": null,
        "equivalentHours": "1.77160583243949415842",
        "stationUnitCount": "24",
        "provinceName": "河南省",
        "monthPower": "155864.37815277782",
        "noAccessNum": "0",
        "yearPlanRate": "213.794656177688492214"
      },
      {
        "stationCode": 76,
        "normalNum": "0",
        "regionName": "河南",
        "latitude": "33.480000000000",
        "alarmNum": "0",
        "yearPower": "174915888",
        "instantaneous": "5.301818181818182",
        "dayPower": "0",
        "yearPlanPower": "230000000.0000",
        "stationPlanPower": "28351.282980184496",
        "stationStatus": {
          "stationStatus": "400",
          "stationStatusName": "通讯正常"
        },
        "standbyNum": "0",
        "stationName": "南召皇后",
        "stationCapacity": "103.2",
        "longitude": "112.770000000000",
        "interruptNum": "44",
        "maintainNum": "0",
        "dayResources": "5.3018184",
        "errorNum": "0",
        "shutdownNum": "0",
        "capabilityRate": "84.399743097073351035",
        "stationPower": "23928.409999999996",
        "equivalentHours": "1",
        "stationUnitCount": "44",
        "provinceName": "河南省",
        "monthPower": "5954750",
        "noAccessNum": "0",
        "yearPlanRate": "76.050386086956521739"
      },
      {
        "stationCode": 74,
        "normalNum": "24",
        "regionName": "安徽",
        "latitude": "33.850000000000",
        "alarmNum": "0",
        "yearPower": "94120322",
        "instantaneous": "7.265",
        "dayPower": "372443",
        "yearPlanPower": "112000000.0000",
        "stationPlanPower": "28016.97172218141186",
        "stationStatus": {
          "stationStatus": "400",
          "stationStatusName": "通讯正常"
        },
        "standbyNum": "0",
        "stationName": "埇桥夹沟",
        "stationCapacity": "48",
        "longitude": "117.020000000000",
        "interruptNum": "0",
        "maintainNum": "0",
        "dayResources": "7.265",
        "errorNum": "0",
        "shutdownNum": "0",
        "capabilityRate": "107.609774171741169262",
        "stationPower": "30149",
        "equivalentHours": "2.05448187995469988675",
        "stationUnitCount": "24",
        "provinceName": "安徽省",
        "monthPower": "5714444",
        "noAccessNum": "0",
        "yearPlanRate": "84.036001785714285714"
      },
      {
        "stationCode": 53,
        "normalNum": "0",
        "regionName": "河南",
        "latitude": "35.680000000000",
        "alarmNum": "0",
        "yearPower": "71548626.57",
        "instantaneous": null,
        "dayPower": null,
        "yearPlanPower": "90000000.0000",
        "stationPlanPower": null,
        "stationStatus": {
          "stationStatus": "500",
          "stationStatusName": "通讯中断"
        },
        "standbyNum": "0",
        "stationName": "浚县火龙岗",
        "stationCapacity": "49.5",
        "longitude": "114.560000000000",
        "interruptNum": "33",
        "maintainNum": "0",
        "dayResources": null,
        "errorNum": "0",
        "shutdownNum": "0",
        "capabilityRate": null,
        "stationPower": null,
        "equivalentHours": "1",
        "stationUnitCount": "33",
        "provinceName": "河南省",
        "monthPower": "3552154",
        "noAccessNum": "0",
        "yearPlanRate": "79.498473966666666667"
      },
      {
        "stationCode": 98,
        "normalNum": "22",
        "regionName": "安徽",
        "latitude": "32.710000000000",
        "alarmNum": "0",
        "yearPower": "97893339",
        "instantaneous": "4.964545454545455",
        "dayPower": "0",
        "yearPlanPower": "119000000.0000",
        "stationPlanPower": "10022.705960008816",
        "stationStatus": {
          "stationStatus": "400",
          "stationStatusName": "通讯正常"
        },
        "standbyNum": "0",
        "stationName": "天长杨村",
        "stationCapacity": "48.4",
        "longitude": "119.090000000000",
        "interruptNum": "0",
        "maintainNum": "0",
        "dayResources": "4.9645452",
        "errorNum": "0",
        "shutdownNum": "0",
        "capabilityRate": "88.365856838847237479",
        "stationPower": "8856.65",
        "equivalentHours": "1",
        "stationUnitCount": "22",
        "provinceName": "安徽省",
        "monthPower": "3118457",
        "noAccessNum": "0",
        "yearPlanRate": "82.263310084033613445"
      },
      {
        "stationCode": 95,
        "normalNum": "0",
        "regionName": "湖南",
        "latitude": "26.180000000000",
        "alarmNum": "0",
        "yearPower": "0",
        "instantaneous": null,
        "dayPower": null,
        "yearPlanPower": null,
        "stationPlanPower": null,
        "stationStatus": {
          "stationStatus": "900",
          "stationStatusName": "未接入"
        },
        "standbyNum": "0",
        "stationName": "通道临口",
        "stationCapacity": "48.8",
        "longitude": "109.980000000000",
        "interruptNum": "23",
        "maintainNum": "0",
        "dayResources": null,
        "errorNum": "0",
        "shutdownNum": "0",
        "capabilityRate": null,
        "stationPower": null,
        "equivalentHours": "1",
        "stationUnitCount": "23",
        "provinceName": "湖南省",
        "monthPower": "0",
        "noAccessNum": "0",
        "yearPlanRate": null
      },
      {
        "stationCode": 83,
        "normalNum": "24",
        "regionName": "湖南",
        "latitude": "25.170000000000",
        "alarmNum": "0",
        "yearPower": "151604637",
        "instantaneous": "10.520833333333334",
        "dayPower": "656140",
        "yearPlanPower": "170000000.0000",
        "stationPlanPower": "44104.93663039908",
        "stationStatus": {
          "stationStatus": "400",
          "stationStatusName": "通讯正常"
        },
        "standbyNum": "0",
        "stationName": "江华桥头铺",
        "stationCapacity": "48",
        "longitude": "111.520000000000",
        "interruptNum": "0",
        "maintainNum": "0",
        "dayResources": "10.520833",
        "errorNum": "0",
        "shutdownNum": "0",
        "capabilityRate": "104.752446165303455143",
        "stationPower": "46201",
        "equivalentHours": "2.19755429822960394233",
        "stationUnitCount": "24",
        "provinceName": "湖南省",
        "monthPower": "11911893",
        "noAccessNum": "0",
        "yearPlanRate": "89.179198235294117647"
      },
      {
        "stationCode": 91,
        "normalNum": "22",
        "regionName": "湖南",
        "latitude": "24.170000000000",
        "alarmNum": "0",
        "yearPower": "80184573",
        "instantaneous": "10.395416666666664",
        "dayPower": "559367",
        "yearPlanPower": "98000000.0000",
        "stationPlanPower": "42561.304351122315",
        "stationStatus": {
          "stationStatus": "400",
          "stationStatusName": "通讯正常"
        },
        "standbyNum": "0",
        "stationName": "江华洪塘",
        "stationCapacity": "48",
        "longitude": "111.420000000000",
        "interruptNum": "0",
        "maintainNum": "0",
        "dayResources": "10.395416",
        "errorNum": "2",
        "shutdownNum": "0",
        "capabilityRate": "94.811473979029772394",
        "stationPower": "40353",
        "equivalentHours": "1.93869273368014767578",
        "stationUnitCount": "24",
        "provinceName": "湖南省",
        "monthPower": "5745331",
        "noAccessNum": "0",
        "yearPlanRate": "81.820992857142857143"
      },
      {
        "stationCode": 59,
        "normalNum": "0",
        "regionName": "湖南",
        "latitude": "25.150000000000",
        "alarmNum": "0",
        "yearPower": "44478690",
        "instantaneous": null,
        "dayPower": null,
        "yearPlanPower": "26000000.0000",
        "stationPlanPower": "10545.75611118829755",
        "stationStatus": {
          "stationStatus": "500",
          "stationStatusName": "通讯中断"
        },
        "standbyNum": "0",
        "stationName": "江华东田",
        "stationCapacity": "48",
        "longitude": "111.650000000000",
        "interruptNum": "24",
        "maintainNum": "0",
        "dayResources": null,
        "errorNum": "0",
        "shutdownNum": "0",
        "capabilityRate": null,
        "stationPower": null,
        "equivalentHours": "1",
        "stationUnitCount": "24",
        "provinceName": "湖南省",
        "monthPower": "0",
        "noAccessNum": "0",
        "yearPlanRate": "171.071884615384615385"
      },
      {
        "stationCode": 51,
        "normalNum": "0",
        "regionName": "湖南",
        "latitude": "25.060000000000",
        "alarmNum": "0",
        "yearPower": "90205720",
        "instantaneous": null,
        "dayPower": null,
        "yearPlanPower": "107000000.0000",
        "stationPlanPower": "24104.89820993125668",
        "stationStatus": {
          "stationStatus": "500",
          "stationStatusName": "通讯中断"
        },
        "standbyNum": "0",
        "stationName": "江华大路铺",
        "stationCapacity": "48",
        "longitude": "111.550000000000",
        "interruptNum": "24",
        "maintainNum": "0",
        "dayResources": null,
        "errorNum": "0",
        "shutdownNum": "0",
        "capabilityRate": null,
        "stationPower": null,
        "equivalentHours": "1",
        "stationUnitCount": "24",
        "provinceName": "湖南省",
        "monthPower": "6984090",
        "noAccessNum": "0",
        "yearPlanRate": "84.304411214953271028"
      },
      {
        "stationCode": 77,
        "normalNum": "24",
        "regionName": "安徽",
        "latitude": "33.110000000000",
        "alarmNum": "0",
        "yearPower": "95614061",
        "instantaneous": "12.242916666666666",
        "dayPower": "519843",
        "yearPlanPower": "116000000.0000",
        "stationPlanPower": "49477.5725445461976",
        "stationStatus": {
          "stationStatus": "400",
          "stationStatusName": "通讯正常"
        },
        "standbyNum": "0",
        "stationName": "五河饮马湖",
        "stationCapacity": "48",
        "longitude": "118.060000000000",
        "interruptNum": "0",
        "maintainNum": "0",
        "dayResources": "12.242917",
        "errorNum": "0",
        "shutdownNum": "0",
        "capabilityRate": "100.255524774057934692",
        "stationPower": "49604",
        "equivalentHours": "1.70258548452493580214",
        "stationUnitCount": "24",
        "provinceName": "安徽省",
        "monthPower": "6299399",
        "noAccessNum": "0",
        "yearPlanRate": "82.425914655172413793"
      },
      {
        "stationCode": 104,
        "normalNum": "23",
        "regionName": "安徽",
        "latitude": "33.110000000000",
        "alarmNum": "0",
        "yearPower": "136464455",
        "instantaneous": "13.805652173913042",
        "dayPower": "674737",
        "yearPlanPower": "150000000.0000",
        "stationPlanPower": "53365.2383059594",
        "stationStatus": {
          "stationStatus": "400",
          "stationStatusName": "通讯正常"
        },
        "standbyNum": "0",
        "stationName": "五河金大山",
        "stationCapacity": "50.6",
        "longitude": "118.060000000000",
        "interruptNum": "0",
        "maintainNum": "0",
        "dayResources": "13.805653",
        "errorNum": "0",
        "shutdownNum": "0",
        "capabilityRate": "98.953985171472449337",
        "stationPower": "52807.03",
        "equivalentHours": "1.85355724225173940544",
        "stationUnitCount": "23",
        "provinceName": "安徽省",
        "monthPower": "8484913",
        "noAccessNum": "0",
        "yearPlanRate": "90.976303333333333333"
      },
      {
        "stationCode": 103,
        "normalNum": "23",
        "regionName": "湖北",
        "latitude": "31.250000000000",
        "alarmNum": "0",
        "yearPower": "116415876",
        "instantaneous": "11.055217391304348",
        "dayPower": "603354",
        "yearPlanPower": "142000000.0000",
        "stationPlanPower": "45483.496379543976",
        "stationStatus": {
          "stationStatus": "400",
          "stationStatusName": "通讯正常"
        },
        "standbyNum": "0",
        "stationName": "栗溪",
        "stationCapacity": "48",
        "longitude": "112.060000000000",
        "interruptNum": "0",
        "maintainNum": "0",
        "dayResources": "11.055218",
        "errorNum": "0",
        "shutdownNum": "0",
        "capabilityRate": "97.977516126139995283",
        "stationPower": "44563.6",
        "equivalentHours": "1.71956350626118067979",
        "stationUnitCount": "23",
        "provinceName": "湖北省",
        "monthPower": "3872097",
        "noAccessNum": "0",
        "yearPlanRate": "81.983011267605633803"
      },
      {
        "stationCode": 102,
        "normalNum": "22",
        "regionName": "湖北",
        "latitude": "31.990000000000",
        "alarmNum": "0",
        "yearPower": "96025896",
        "instantaneous": "6.159999999999999",
        "dayPower": "396217",
        "yearPlanPower": "105000000.0000",
        "stationPlanPower": "18200.327654784116",
        "stationStatus": {
          "stationStatus": "400",
          "stationStatusName": "通讯正常"
        },
        "standbyNum": "0",
        "stationName": "襄州峪山一期",
        "stationCapacity": "46",
        "longitude": "112.370000000000",
        "interruptNum": "0",
        "maintainNum": "0",
        "dayResources": "6.16",
        "errorNum": "0",
        "shutdownNum": "0",
        "capabilityRate": "133.953632387444974598",
        "stationPower": "24380",
        "equivalentHours": "1.44795590729225551159",
        "stationUnitCount": "23",
        "provinceName": "湖北省",
        "monthPower": "2982235",
        "noAccessNum": "0",
        "yearPlanRate": "91.453234285714285714"
      },
      {
        "stationCode": 93,
        "normalNum": "23",
        "regionName": "湖北",
        "latitude": "31.250000000000",
        "alarmNum": "0",
        "yearPower": "102135108",
        "instantaneous": "9.730833333333331",
        "dayPower": "484317",
        "yearPlanPower": "136000000.0000",
        "stationPlanPower": "43884.58904294357",
        "stationStatus": {
          "stationStatus": "400",
          "stationStatusName": "通讯正常"
        },
        "standbyNum": "0",
        "stationName": "圣境山",
        "stationCapacity": "52.8",
        "longitude": "112.060000000000",
        "interruptNum": "0",
        "maintainNum": "1",
        "dayResources": "9.730833",
        "errorNum": "0",
        "shutdownNum": "0",
        "capabilityRate": "96.095237347974876745",
        "stationPower": "42171",
        "equivalentHours": "1.51671503254027525872",
        "stationUnitCount": "24",
        "provinceName": "湖北省",
        "monthPower": "3192344",
        "noAccessNum": "0",
        "yearPlanRate": "75.099344117647058824"
      },
      {
        "stationCode": 79,
        "normalNum": "24",
        "regionName": "广西",
        "latitude": "25.040000000000",
        "alarmNum": "0",
        "yearPower": "112746380",
        "instantaneous": "10",
        "dayPower": "639970",
        "yearPlanPower": "109000000.0000",
        "stationPlanPower": "40586.89854555916",
        "stationStatus": {
          "stationStatus": "400",
          "stationStatusName": "通讯正常"
        },
        "standbyNum": "0",
        "stationName": "富川朝东",
        "stationCapacity": "48",
        "longitude": "111.220000000000",
        "interruptNum": "0",
        "maintainNum": "0",
        "dayResources": "10.0",
        "errorNum": "0",
        "shutdownNum": "0",
        "capabilityRate": "105.489706122629143501",
        "stationPower": "42815",
        "equivalentHours": "1.6495179133258905917",
        "stationUnitCount": "24",
        "provinceName": "广西省",
        "monthPower": "8246210",
        "noAccessNum": "0",
        "yearPlanRate": "103.437045871559633028"
      },
      {
        "stationCode": 80,
        "normalNum": "24",
        "regionName": "广西",
        "latitude": "25.000000000000",
        "alarmNum": "0",
        "yearPower": "118730587",
        "instantaneous": "10.458333333333336",
        "dayPower": "569590",
        "yearPlanPower": "104000000.0000",
        "stationPlanPower": "44896.83721630788",
        "stationStatus": {
          "stationStatus": "400",
          "stationStatusName": "通讯正常"
        },
        "standbyNum": "0",
        "stationName": "富川石家",
        "stationCapacity": "48",
        "longitude": "111.240000000000",
        "interruptNum": "0",
        "maintainNum": "0",
        "dayResources": "10.458333",
        "errorNum": "0",
        "shutdownNum": "0",
        "capabilityRate": "96.463365094833161603",
        "stationPower": "43309",
        "equivalentHours": "1.55123391077131520372",
        "stationUnitCount": "24",
        "provinceName": "广西省",
        "monthPower": "8200743",
        "noAccessNum": "0",
        "yearPlanRate": "114.164025961538461538"
      },
      {
        "stationCode": 99,
        "normalNum": "18",
        "regionName": "广西",
        "latitude": "25.040000000000",
        "alarmNum": "0",
        "yearPower": "93385776",
        "instantaneous": "8.31111111111111",
        "dayPower": "461155",
        "yearPlanPower": "86000000.0000",
        "stationPlanPower": "34763.39199471484",
        "stationStatus": {
          "stationStatus": "400",
          "stationStatusName": "通讯正常"
        },
        "standbyNum": "4",
        "stationName": "富川新造",
        "stationCapacity": "48.4",
        "longitude": "111.220000000000",
        "interruptNum": "0",
        "maintainNum": "0",
        "dayResources": "8.311111",
        "errorNum": "0",
        "shutdownNum": "0",
        "capabilityRate": "103.43412405057210456",
        "stationPower": "35957.21",
        "equivalentHours": "1.42632430433576777295",
        "stationUnitCount": "22",
        "provinceName": "广西省",
        "monthPower": "7720153",
        "noAccessNum": "0",
        "yearPlanRate": "108.588111627906976744"
      },
      {
        "stationCode": 96,
        "normalNum": "0",
        "regionName": "湖南",
        "latitude": "26.180000000000",
        "alarmNum": "0",
        "yearPower": "0",
        "instantaneous": null,
        "dayPower": null,
        "yearPlanPower": null,
        "stationPlanPower": null,
        "stationStatus": {
          "stationStatus": "900",
          "stationStatusName": "未接入"
        },
        "standbyNum": "0",
        "stationName": "通道传素",
        "stationCapacity": "32.6",
        "longitude": "109.980000000000",
        "interruptNum": "16",
        "maintainNum": "0",
        "dayResources": null,
        "errorNum": "0",
        "shutdownNum": "0",
        "capabilityRate": null,
        "stationPower": null,
        "equivalentHours": "1",
        "stationUnitCount": "16",
        "provinceName": "湖南省",
        "monthPower": "0",
        "noAccessNum": "0",
        "yearPlanRate": null
      },
      {
        "stationCode": 27,
        "normalNum": "0",
        "regionName": "蒙东",
        "latitude": "43.240000000000",
        "alarmNum": "0",
        "yearPower": "102972225",
        "instantaneous": null,
        "dayPower": null,
        "yearPlanPower": "107000000.0000",
        "stationPlanPower": null,
        "stationStatus": {
          "stationStatus": "900",
          "stationStatusName": "未接入"
        },
        "standbyNum": "0",
        "stationName": "花灯一期",
        "stationCapacity": "49.5",
        "longitude": "122.170000000000",
        "interruptNum": "33",
        "maintainNum": "0",
        "dayResources": null,
        "errorNum": "0",
        "shutdownNum": "0",
        "capabilityRate": null,
        "stationPower": null,
        "equivalentHours": "1",
        "stationUnitCount": "33",
        "provinceName": "内蒙古自治区",
        "monthPower": "9068421",
        "noAccessNum": "0",
        "yearPlanRate": "96.235724299065420561"
      },
      {
        "stationCode": 105,
        "normalNum": "0",
        "regionName": "河南",
        "latitude": "33.323000000000",
        "alarmNum": "0",
        "yearPower": "103542283",
        "instantaneous": null,
        "dayPower": null,
        "yearPlanPower": "45000000.0000",
        "stationPlanPower": "1195.05494145991233232",
        "stationStatus": {
          "stationStatus": "500",
          "stationStatusName": "通讯中断"
        },
        "standbyNum": "0",
        "stationName": "南召花园",
        "stationCapacity": "100",
        "longitude": "112.431400000000",
        "interruptNum": "39",
        "maintainNum": "0",
        "dayResources": null,
        "errorNum": "0",
        "shutdownNum": "0",
        "capabilityRate": null,
        "stationPower": null,
        "equivalentHours": "1",
        "stationUnitCount": "39",
        "provinceName": "河南省",
        "monthPower": "0",
        "noAccessNum": "0",
        "yearPlanRate": "230.093962222222222222"
      },
      {
        "stationCode": 54,
        "normalNum": "0",
        "regionName": "安徽",
        "latitude": "34.046667000000",
        "alarmNum": null,
        "yearPower": "75266481",
        "instantaneous": null,
        "dayPower": null,
        "yearPlanPower": "98000000.0000",
        "stationPlanPower": null,
        "stationStatus": {
          "stationStatus": "900",
          "stationStatusName": "未接入"
        },
        "standbyNum": "0",
        "stationName": "萧县官山风电场",
        "stationCapacity": "48",
        "longitude": "116.993461000000",
        "interruptNum": "24",
        "maintainNum": "0",
        "dayResources": null,
        "errorNum": "0",
        "shutdownNum": "0",
        "capabilityRate": null,
        "stationPower": null,
        "equivalentHours": "1",
        "stationUnitCount": "24",
        "provinceName": "安徽省",
        "monthPower": "4835932",
        "noAccessNum": "0",
        "yearPlanRate": "76.802531632653061224"
      },
      {
        "stationCode": 72,
        "normalNum": "0",
        "regionName": "安徽",
        "latitude": "34.046667000000",
        "alarmNum": null,
        "yearPower": "90885913",
        "instantaneous": null,
        "dayPower": null,
        "yearPlanPower": "115000000.0000",
        "stationPlanPower": null,
        "stationStatus": {
          "stationStatus": "900",
          "stationStatusName": "未接入"
        },
        "standbyNum": "0",
        "stationName": "萧县灵山风电场",
        "stationCapacity": "48",
        "longitude": "116.993461000000",
        "interruptNum": "24",
        "maintainNum": "0",
        "dayResources": null,
        "errorNum": "0",
        "shutdownNum": "0",
        "capabilityRate": null,
        "stationPower": null,
        "equivalentHours": "1",
        "stationUnitCount": "24",
        "provinceName": "安徽省",
        "monthPower": "5706452",
        "noAccessNum": "0",
        "yearPlanRate": "79.031228695652173913"
      },
      {
        "stationCode": 57,
        "normalNum": "0",
        "regionName": "安徽",
        "latitude": "33.760000000000",
        "alarmNum": null,
        "yearPower": "89267219",
        "instantaneous": null,
        "dayPower": null,
        "yearPlanPower": "108000000.0000",
        "stationPlanPower": null,
        "stationStatus": {
          "stationStatus": "900",
          "stationStatusName": "未接入"
        },
        "standbyNum": "0",
        "stationName": "埇桥符离",
        "stationCapacity": "48",
        "longitude": "116.990000000000",
        "interruptNum": "24",
        "maintainNum": "0",
        "dayResources": null,
        "errorNum": "0",
        "shutdownNum": "0",
        "capabilityRate": null,
        "stationPower": null,
        "equivalentHours": "1",
        "stationUnitCount": "24",
        "provinceName": "安徽省",
        "monthPower": "5378485",
        "noAccessNum": "0",
        "yearPlanRate": "82.654832407407407407"
      },
      {
        "stationCode": 28,
        "normalNum": "0",
        "regionName": "蒙东",
        "latitude": "43.000000000000",
        "alarmNum": null,
        "yearPower": "103625166",
        "instantaneous": null,
        "dayPower": null,
        "yearPlanPower": "116000000.0000",
        "stationPlanPower": null,
        "stationStatus": {
          "stationStatus": "900",
          "stationStatusName": "未接入"
        },
        "standbyNum": "0",
        "stationName": "花灯二期",
        "stationCapacity": "49.5",
        "longitude": "122.000000000000",
        "interruptNum": "33",
        "maintainNum": "0",
        "dayResources": null,
        "errorNum": "0",
        "shutdownNum": "0",
        "capabilityRate": null,
        "stationPower": null,
        "equivalentHours": "1",
        "stationUnitCount": "33",
        "provinceName": "内蒙古自治区",
        "monthPower": "8696703",
        "noAccessNum": "0",
        "yearPlanRate": "89.332039655172413793"
      },
      {
        "stationCode": 30,
        "normalNum": "0",
        "regionName": "蒙东",
        "latitude": "43.780000000000",
        "alarmNum": null,
        "yearPower": "89635600",
        "instantaneous": null,
        "dayPower": null,
        "yearPlanPower": "114000000.0000",
        "stationPlanPower": null,
        "stationStatus": {
          "stationStatus": "900",
          "stationStatusName": "未接入"
        },
        "standbyNum": "0",
        "stationName": "开鲁建华一期",
        "stationCapacity": "49.5",
        "longitude": "121.400000000000",
        "interruptNum": "33",
        "maintainNum": "0",
        "dayResources": null,
        "errorNum": "0",
        "shutdownNum": "0",
        "capabilityRate": null,
        "stationPower": null,
        "equivalentHours": "1",
        "stationUnitCount": "33",
        "provinceName": "内蒙古自治区",
        "monthPower": "6458340",
        "noAccessNum": "0",
        "yearPlanRate": "78.627719298245614035"
      },
      {
        "stationCode": 40,
        "normalNum": "0",
        "regionName": "安徽",
        "latitude": "32.720000000000",
        "alarmNum": null,
        "yearPower": "55336659",
        "instantaneous": null,
        "dayPower": null,
        "yearPlanPower": "76000000.0000",
        "stationPlanPower": null,
        "stationStatus": {
          "stationStatus": "900",
          "stationStatusName": "未接入"
        },
        "standbyNum": "0",
        "stationName": "天长一期",
        "stationCapacity": "48",
        "longitude": "119.090000000000",
        "interruptNum": "24",
        "maintainNum": "0",
        "dayResources": null,
        "errorNum": "0",
        "shutdownNum": "0",
        "capabilityRate": null,
        "stationPower": null,
        "equivalentHours": "1",
        "stationUnitCount": "24",
        "provinceName": "安徽省",
        "monthPower": "2617941",
        "noAccessNum": "0",
        "yearPlanRate": "72.811393421052631579"
      },
      {
        "stationCode": 11,
        "normalNum": "0",
        "regionName": "蒙西",
        "latitude": "41.476540000000",
        "alarmNum": "2",
        "yearPower": "83468059",
        "instantaneous": null,
        "dayPower": null,
        "yearPlanPower": "105000000.0000",
        "stationPlanPower": null,
        "stationStatus": {
          "stationStatus": "500",
          "stationStatusName": "通讯中断"
        },
        "standbyNum": "0",
        "stationName": "太旗贡宝拉格",
        "stationCapacity": "49.5",
        "longitude": "115.161100000000",
        "interruptNum": "66",
        "maintainNum": "0",
        "dayResources": null,
        "errorNum": "0",
        "shutdownNum": "0",
        "capabilityRate": null,
        "stationPower": null,
        "equivalentHours": "1",
        "stationUnitCount": "66",
        "provinceName": "内蒙古自治区",
        "monthPower": "6519883",
        "noAccessNum": "0",
        "yearPlanRate": "79.49338952380952381"
      },
      {
        "stationCode": 100,
        "normalNum": "22",
        "regionName": "湖南",
        "latitude": "25.340000000000",
        "alarmNum": "0",
        "yearPower": "76798698.5",
        "instantaneous": "9.650416666666667",
        "dayPower": "349454.5",
        "yearPlanPower": "97000000.0000",
        "stationPlanPower": "42450.52467064443",
        "stationStatus": {
          "stationStatus": "400",
          "stationStatusName": "通讯正常"
        },
        "standbyNum": "0",
        "stationName": "审章塘",
        "stationCapacity": "48",
        "longitude": "111.610000000000",
        "interruptNum": "0",
        "maintainNum": "0",
        "dayResources": "9.650416",
        "errorNum": "2",
        "shutdownNum": "0",
        "capabilityRate": "58.467828590028142454",
        "stationPower": "24819.899999999994",
        "equivalentHours": "1.21149579374205652727",
        "stationUnitCount": "24",
        "provinceName": "湖南省",
        "monthPower": "5146282.5",
        "noAccessNum": "0",
        "yearPlanRate": "79.173915979381443299"
      },
      {
        "stationCode": 32,
        "normalNum": "0",
        "regionName": "蒙西",
        "latitude": "40.970000000000",
        "alarmNum": "0",
        "yearPower": "109426824",
        "instantaneous": null,
        "dayPower": null,
        "yearPlanPower": "141000000.0000",
        "stationPlanPower": null,
        "stationStatus": {
          "stationStatus": "500",
          "stationStatusName": "通讯中断"
        },
        "standbyNum": "0",
        "stationName": "头支箭一期",
        "stationCapacity": "49.5",
        "longitude": "111.140000000000",
        "interruptNum": "33",
        "maintainNum": "0",
        "dayResources": null,
        "errorNum": "0",
        "shutdownNum": "0",
        "capabilityRate": null,
        "stationPower": null,
        "equivalentHours": "1",
        "stationUnitCount": "33",
        "provinceName": "内蒙古自治区",
        "monthPower": "8951090",
        "noAccessNum": "0",
        "yearPlanRate": "77.607676595744680851"
      },
      {
        "stationCode": 16,
        "normalNum": "0",
        "regionName": "蒙东",
        "latitude": "44.560000000000",
        "alarmNum": null,
        "yearPower": "99771840",
        "instantaneous": null,
        "dayPower": null,
        "yearPlanPower": "117000000.0000",
        "stationPlanPower": null,
        "stationStatus": {
          "stationStatus": "900",
          "stationStatusName": "未接入"
        },
        "standbyNum": "0",
        "stationName": "扎旗一期",
        "stationCapacity": "49.5",
        "longitude": "120.920000000000",
        "interruptNum": "33",
        "maintainNum": "0",
        "dayResources": null,
        "errorNum": "0",
        "shutdownNum": "0",
        "capabilityRate": null,
        "stationPower": null,
        "equivalentHours": "1",
        "stationUnitCount": "33",
        "provinceName": "内蒙古自治区",
        "monthPower": "7456680",
        "noAccessNum": "0",
        "yearPlanRate": "85.275076923076923077"
      },
      {
        "stationCode": 17,
        "normalNum": "0",
        "regionName": "蒙东",
        "latitude": "44.560000000000",
        "alarmNum": null,
        "yearPower": "122398920",
        "instantaneous": null,
        "dayPower": null,
        "yearPlanPower": "138000000.0000",
        "stationPlanPower": null,
        "stationStatus": {
          "stationStatus": "900",
          "stationStatusName": "未接入"
        },
        "standbyNum": "0",
        "stationName": "扎旗二期",
        "stationCapacity": "49.5",
        "longitude": "120.920000000000",
        "interruptNum": "33",
        "maintainNum": "0",
        "dayResources": null,
        "errorNum": "0",
        "shutdownNum": "0",
        "capabilityRate": null,
        "stationPower": null,
        "equivalentHours": "1",
        "stationUnitCount": "33",
        "provinceName": "内蒙古自治区",
        "monthPower": "8993320",
        "noAccessNum": "0",
        "yearPlanRate": "88.694869565217391304"
      },
      {
        "stationCode": 18,
        "normalNum": "0",
        "regionName": "蒙东",
        "latitude": "44.560000000000",
        "alarmNum": null,
        "yearPower": "102743480",
        "instantaneous": null,
        "dayPower": null,
        "yearPlanPower": "114000000.0000",
        "stationPlanPower": null,
        "stationStatus": {
          "stationStatus": "900",
          "stationStatusName": "未接入"
        },
        "standbyNum": "0",
        "stationName": "扎旗三期",
        "stationCapacity": "49.5",
        "longitude": "120.920000000000",
        "interruptNum": "33",
        "maintainNum": "0",
        "dayResources": null,
        "errorNum": "0",
        "shutdownNum": "0",
        "capabilityRate": null,
        "stationPower": null,
        "equivalentHours": "1",
        "stationUnitCount": "33",
        "provinceName": "内蒙古自治区",
        "monthPower": "8041040",
        "noAccessNum": "0",
        "yearPlanRate": "90.125859649122807018"
      },
      {
        "stationCode": 21,
        "normalNum": "0",
        "regionName": "甘肃",
        "latitude": "40.670000000000",
        "alarmNum": null,
        "yearPower": "274821584",
        "instantaneous": null,
        "dayPower": null,
        "yearPlanPower": "320000000.0000",
        "stationPlanPower": null,
        "stationStatus": {
          "stationStatus": "900",
          "stationStatusName": "未接入"
        },
        "standbyNum": "0",
        "stationName": "瓜州干河口",
        "stationCapacity": "201",
        "longitude": "95.350000000000",
        "interruptNum": "134",
        "maintainNum": "0",
        "dayResources": null,
        "errorNum": "0",
        "shutdownNum": "0",
        "capabilityRate": null,
        "stationPower": null,
        "equivalentHours": "1",
        "stationUnitCount": "134",
        "provinceName": "甘肃省",
        "monthPower": "6722020",
        "noAccessNum": "0",
        "yearPlanRate": "85.881745"
      },
      {
        "stationCode": 15,
        "normalNum": "0",
        "regionName": "蒙西",
        "latitude": "41.186100000000",
        "alarmNum": "0",
        "yearPower": "89788761",
        "instantaneous": null,
        "dayPower": null,
        "yearPlanPower": "117000000.0000",
        "stationPlanPower": null,
        "stationStatus": {
          "stationStatus": "500",
          "stationStatusName": "通讯中断"
        },
        "standbyNum": "0",
        "stationName": "武川义合",
        "stationCapacity": "49.5",
        "longitude": "110.946100000000",
        "interruptNum": "33",
        "maintainNum": "0",
        "dayResources": null,
        "errorNum": "0",
        "shutdownNum": "0",
        "capabilityRate": null,
        "stationPower": null,
        "equivalentHours": "1",
        "stationUnitCount": "33",
        "provinceName": "内蒙古自治区",
        "monthPower": "6239119",
        "noAccessNum": "0",
        "yearPlanRate": "76.742530769230769231"
      },
      {
        "stationCode": 25,
        "normalNum": "0",
        "regionName": "吉林",
        "latitude": "45.840000000000",
        "alarmNum": null,
        "yearPower": "0",
        "instantaneous": null,
        "dayPower": null,
        "yearPlanPower": null,
        "stationPlanPower": null,
        "stationStatus": {
          "stationStatus": "900",
          "stationStatusName": "未接入"
        },
        "standbyNum": "0",
        "stationName": "黑鱼泡四期",
        "stationCapacity": "49.5",
        "longitude": "123.370000000000",
        "interruptNum": "33",
        "maintainNum": "0",
        "dayResources": null,
        "errorNum": "0",
        "shutdownNum": "0",
        "capabilityRate": null,
        "stationPower": null,
        "equivalentHours": "1",
        "stationUnitCount": "33",
        "provinceName": "吉林省",
        "monthPower": "0",
        "noAccessNum": "0",
        "yearPlanRate": null
      },
      {
        "stationCode": 24,
        "normalNum": "0",
        "regionName": "吉林",
        "latitude": "45.840000000000",
        "alarmNum": null,
        "yearPower": "0",
        "instantaneous": null,
        "dayPower": null,
        "yearPlanPower": null,
        "stationPlanPower": null,
        "stationStatus": {
          "stationStatus": "900",
          "stationStatusName": "未接入"
        },
        "standbyNum": "0",
        "stationName": "黑鱼泡三期",
        "stationCapacity": "49.5",
        "longitude": "123.370000000000",
        "interruptNum": "33",
        "maintainNum": "0",
        "dayResources": null,
        "errorNum": "0",
        "shutdownNum": "0",
        "capabilityRate": null,
        "stationPower": null,
        "equivalentHours": "1",
        "stationUnitCount": "33",
        "provinceName": "吉林省",
        "monthPower": "0",
        "noAccessNum": "0",
        "yearPlanRate": null
      },
      {
        "stationCode": 4,
        "normalNum": "0",
        "regionName": "辽宁",
        "latitude": "42.553300000000",
        "alarmNum": null,
        "yearPower": "104106258",
        "instantaneous": null,
        "dayPower": null,
        "yearPlanPower": "132000000.0000",
        "stationPlanPower": null,
        "stationStatus": {
          "stationStatus": "900",
          "stationStatusName": "未接入"
        },
        "standbyNum": "0",
        "stationName": "彰东马鬃山",
        "stationCapacity": "49.5",
        "longitude": "122.798900000000",
        "interruptNum": "33",
        "maintainNum": "0",
        "dayResources": null,
        "errorNum": "0",
        "shutdownNum": "0",
        "capabilityRate": null,
        "stationPower": null,
        "equivalentHours": "1",
        "stationUnitCount": "33",
        "provinceName": "辽宁省",
        "monthPower": "7958462",
        "noAccessNum": "0",
        "yearPlanRate": "78.868377272727272727"
      },
      {
        "stationCode": 6,
        "normalNum": "0",
        "regionName": "辽宁",
        "latitude": "42.553300000000",
        "alarmNum": null,
        "yearPower": "93294130",
        "instantaneous": null,
        "dayPower": null,
        "yearPlanPower": "115000000.0000",
        "stationPlanPower": null,
        "stationStatus": {
          "stationStatus": "900",
          "stationStatusName": "未接入"
        },
        "standbyNum": "0",
        "stationName": "彰东曲家沟",
        "stationCapacity": "49.5",
        "longitude": "122.798900000000",
        "interruptNum": "33",
        "maintainNum": "0",
        "dayResources": null,
        "errorNum": "0",
        "shutdownNum": "0",
        "capabilityRate": null,
        "stationPower": null,
        "equivalentHours": "1",
        "stationUnitCount": "33",
        "provinceName": "辽宁省",
        "monthPower": "7078175",
        "noAccessNum": "0",
        "yearPlanRate": "81.125330434782608696"
      },
      {
        "stationCode": 7,
        "normalNum": "0",
        "regionName": "蒙西",
        "latitude": "43.650000000000",
        "alarmNum": null,
        "yearPower": "38701540",
        "instantaneous": null,
        "dayPower": null,
        "yearPlanPower": "42000000.0000",
        "stationPlanPower": null,
        "stationStatus": {
          "stationStatus": "900",
          "stationStatusName": "未接入"
        },
        "standbyNum": "0",
        "stationName": "二连长风",
        "stationCapacity": "21",
        "longitude": "111.960000000000",
        "interruptNum": "14",
        "maintainNum": "0",
        "dayResources": null,
        "errorNum": "0",
        "shutdownNum": "0",
        "capabilityRate": null,
        "stationPower": null,
        "equivalentHours": "1",
        "stationUnitCount": "14",
        "provinceName": "内蒙古自治区",
        "monthPower": "2380400",
        "noAccessNum": "0",
        "yearPlanRate": "92.146523809523809524"
      },
      {
        "stationCode": 22,
        "normalNum": "0",
        "regionName": "吉林",
        "latitude": "45.840000000000",
        "alarmNum": null,
        "yearPower": "80925254",
        "instantaneous": null,
        "dayPower": null,
        "yearPlanPower": "92000000.0000",
        "stationPlanPower": null,
        "stationStatus": {
          "stationStatus": "900",
          "stationStatusName": "未接入"
        },
        "standbyNum": "0",
        "stationName": "黑鱼泡一期",
        "stationCapacity": "49.5",
        "longitude": "123.370000000000",
        "interruptNum": "33",
        "maintainNum": "0",
        "dayResources": null,
        "errorNum": "0",
        "shutdownNum": "0",
        "capabilityRate": null,
        "stationPower": null,
        "equivalentHours": "1",
        "stationUnitCount": "33",
        "provinceName": "吉林省",
        "monthPower": "7340118",
        "noAccessNum": "0",
        "yearPlanRate": "87.962232608695652174"
      },
      {
        "stationCode": 55,
        "normalNum": "0",
        "regionName": "山东",
        "latitude": "37.497657000000",
        "alarmNum": null,
        "yearPower": "62466300",
        "instantaneous": null,
        "dayPower": null,
        "yearPlanPower": "87000000.0000",
        "stationPlanPower": null,
        "stationStatus": {
          "stationStatus": "900",
          "stationStatusName": "未接入"
        },
        "standbyNum": "0",
        "stationName": "福山亿豪",
        "stationCapacity": "48",
        "longitude": "121.143412000000",
        "interruptNum": "24",
        "maintainNum": "0",
        "dayResources": null,
        "errorNum": "0",
        "shutdownNum": "0",
        "capabilityRate": null,
        "stationPower": null,
        "equivalentHours": "1",
        "stationUnitCount": "24",
        "provinceName": "山东省",
        "monthPower": "3364900",
        "noAccessNum": "0",
        "yearPlanRate": "71.800344827586206897"
      },
      {
        "stationCode": 106,
        "normalNum": "0",
        "regionName": "安徽",
        "latitude": "34.052000000000",
        "alarmNum": "0",
        "yearPower": "0",
        "instantaneous": null,
        "dayPower": null,
        "yearPlanPower": null,
        "stationPlanPower": null,
        "stationStatus": {
          "stationStatus": "900",
          "stationStatusName": "未接入"
        },
        "standbyNum": "0",
        "stationName": "宿州秦山",
        "stationCapacity": "33",
        "longitude": "117.616000000000",
        "interruptNum": "12",
        "maintainNum": "0",
        "dayResources": null,
        "errorNum": "0",
        "shutdownNum": "0",
        "capabilityRate": null,
        "stationPower": null,
        "equivalentHours": "1",
        "stationUnitCount": "12",
        "provinceName": "安徽省",
        "monthPower": "0",
        "noAccessNum": "0",
        "yearPlanRate": null
      },
      {
        "stationCode": 13,
        "normalNum": "0",
        "regionName": "吉林",
        "latitude": "46.020000000000",
        "alarmNum": null,
        "yearPower": "84218339.63",
        "instantaneous": null,
        "dayPower": null,
        "yearPlanPower": "94000000.0000",
        "stationPlanPower": null,
        "stationStatus": {
          "stationStatus": "900",
          "stationStatusName": "未接入"
        },
        "standbyNum": "0",
        "stationName": "镇赉林场一期",
        "stationCapacity": "49.5",
        "longitude": "122.970000000000",
        "interruptNum": "33",
        "maintainNum": "0",
        "dayResources": null,
        "errorNum": "0",
        "shutdownNum": "0",
        "capabilityRate": null,
        "stationPower": null,
        "equivalentHours": "1",
        "stationUnitCount": "33",
        "provinceName": "吉林省",
        "monthPower": "6314958",
        "noAccessNum": "0",
        "yearPlanRate": "89.593978329787234043"
      },
      {
        "stationCode": 52,
        "normalNum": "24",
        "regionName": "湖北",
        "latitude": "31.130000000000",
        "alarmNum": "0",
        "yearPower": "58814800",
        "instantaneous": "9.429166666666664",
        "dayPower": "407020",
        "yearPlanPower": "75000000.0000",
        "stationPlanPower": "38566.5713261135835",
        "stationStatus": {
          "stationStatus": "400",
          "stationStatusName": "通讯正常"
        },
        "standbyNum": "0",
        "stationName": "荆门子陵铺",
        "stationCapacity": "48",
        "longitude": "112.230000000000",
        "interruptNum": "0",
        "maintainNum": "0",
        "dayResources": "9.429167",
        "errorNum": "0",
        "shutdownNum": "0",
        "capabilityRate": "102.850729624341764701",
        "stationPower": "39666",
        "equivalentHours": "1.15975351283460240207",
        "stationUnitCount": "24",
        "provinceName": "湖北省",
        "monthPower": "1538080",
        "noAccessNum": "0",
        "yearPlanRate": "78.419733333333333333"
      },
      {
        "stationCode": 35,
        "normalNum": "0",
        "regionName": "辽宁",
        "latitude": "42.270000000000",
        "alarmNum": null,
        "yearPower": "94434139",
        "instantaneous": null,
        "dayPower": null,
        "yearPlanPower": "118000000.0000",
        "stationPlanPower": null,
        "stationStatus": {
          "stationStatus": "900",
          "stationStatusName": "未接入"
        },
        "standbyNum": "0",
        "stationName": "阜西古力本皋",
        "stationCapacity": "49.5",
        "longitude": "121.360000000000",
        "interruptNum": "33",
        "maintainNum": "0",
        "dayResources": null,
        "errorNum": "0",
        "shutdownNum": "0",
        "capabilityRate": null,
        "stationPower": null,
        "equivalentHours": "1",
        "stationUnitCount": "33",
        "provinceName": "辽宁省",
        "monthPower": "4841213",
        "noAccessNum": "0",
        "yearPlanRate": "80.02893135593220339"
      },
      {
        "stationCode": 33,
        "normalNum": "0",
        "regionName": "辽宁",
        "latitude": "42.270000000000",
        "alarmNum": null,
        "yearPower": "96771520",
        "instantaneous": null,
        "dayPower": null,
        "yearPlanPower": "117000000.0000",
        "stationPlanPower": null,
        "stationStatus": {
          "stationStatus": "900",
          "stationStatusName": "未接入"
        },
        "standbyNum": "0",
        "stationName": "阜西马牛虎",
        "stationCapacity": "49.5",
        "longitude": "121.360000000000",
        "interruptNum": "33",
        "maintainNum": "0",
        "dayResources": null,
        "errorNum": "0",
        "shutdownNum": "0",
        "capabilityRate": null,
        "stationPower": null,
        "equivalentHours": "1",
        "stationUnitCount": "33",
        "provinceName": "辽宁省",
        "monthPower": "5039275",
        "noAccessNum": "0",
        "yearPlanRate": "82.710700854700854701"
      },
      {
        "stationCode": 31,
        "normalNum": "0",
        "regionName": "辽宁",
        "latitude": "42.120000000000",
        "alarmNum": null,
        "yearPower": "132423917",
        "instantaneous": null,
        "dayPower": null,
        "yearPlanPower": "156000000.0000",
        "stationPlanPower": null,
        "stationStatus": {
          "stationStatus": "900",
          "stationStatusName": "未接入"
        },
        "standbyNum": "0",
        "stationName": "万家营子",
        "stationCapacity": "49.5",
        "longitude": "119.690000000000",
        "interruptNum": "33",
        "maintainNum": "0",
        "dayResources": null,
        "errorNum": "0",
        "shutdownNum": "0",
        "capabilityRate": null,
        "stationPower": null,
        "equivalentHours": "1",
        "stationUnitCount": "33",
        "provinceName": "辽宁省",
        "monthPower": "8601304",
        "noAccessNum": "0",
        "yearPlanRate": "84.887126282051282051"
      },
      {
        "stationCode": 10,
        "normalNum": "0",
        "regionName": "辽宁",
        "latitude": "42.790000000000",
        "alarmNum": null,
        "yearPower": "47256813",
        "instantaneous": null,
        "dayPower": null,
        "yearPlanPower": "72000000.0000",
        "stationPlanPower": null,
        "stationStatus": {
          "stationStatus": "900",
          "stationStatusName": "未接入"
        },
        "standbyNum": "0",
        "stationName": "昌图辽能协鑫",
        "stationCapacity": "50.25",
        "longitude": "124.120000000000",
        "interruptNum": "67",
        "maintainNum": "0",
        "dayResources": null,
        "errorNum": "0",
        "shutdownNum": "0",
        "capabilityRate": null,
        "stationPower": null,
        "equivalentHours": "1",
        "stationUnitCount": "67",
        "provinceName": "辽宁省",
        "monthPower": "3413089",
        "noAccessNum": "0",
        "yearPlanRate": "65.6344625"
      },
      {
        "stationCode": 101,
        "normalNum": "23",
        "regionName": "湖南",
        "latitude": "25.350000000000",
        "alarmNum": "0",
        "yearPower": "83653279.5",
        "instantaneous": "10.889130434782608",
        "dayPower": "388414.5",
        "yearPlanPower": "96000000.0000",
        "stationPlanPower": "42377.7312869744601",
        "stationStatus": {
          "stationStatus": "400",
          "stationStatusName": "通讯正常"
        },
        "standbyNum": "1",
        "stationName": "井塘",
        "stationCapacity": "48",
        "longitude": "111.620000000000",
        "interruptNum": "0",
        "maintainNum": "0",
        "dayResources": "10.889131",
        "errorNum": "0",
        "shutdownNum": "0",
        "capabilityRate": "63.786803066327841586",
        "stationPower": "27031.399999999998",
        "equivalentHours": "1.13898999838972285341",
        "stationUnitCount": "24",
        "provinceName": "湖南省",
        "monthPower": "5238663.5",
        "noAccessNum": "0",
        "yearPlanRate": "87.1388328125"
      },
      {
        "stationCode": 107,
        "normalNum": "3",
        "regionName": "湖北",
        "latitude": "32.204451000000",
        "alarmNum": "0",
        "yearPower": "82025114",
        "instantaneous": "2.42",
        "dayPower": "270244",
        "yearPlanPower": "103000000.0000",
        "stationPlanPower": "2038.6470104380023",
        "stationStatus": {
          "stationStatus": "400",
          "stationStatusName": "通讯正常"
        },
        "standbyNum": "11",
        "stationName": "枣阳新市",
        "stationCapacity": "47",
        "longitude": "113.031115000000",
        "interruptNum": "0",
        "maintainNum": "0",
        "dayResources": "2.42",
        "errorNum": "1",
        "shutdownNum": "0",
        "capabilityRate": "0",
        "stationPower": "0",
        "equivalentHours": "1.09510443244004152663",
        "stationUnitCount": "16",
        "provinceName": "湖北省",
        "monthPower": "3348321",
        "noAccessNum": "1",
        "yearPlanRate": "79.636033009708737864"
      },
      {
        "stationCode": 3344113,
        "normalNum": "21",
        "regionName": "湖南",
        "latitude": "25.400000000000",
        "alarmNum": "0",
        "yearPower": "83147280",
        "instantaneous": "9.704545454545455",
        "dayPower": "458060",
        "yearPlanPower": "98000000.0000",
        "stationPlanPower": "43000.2206627257603",
        "stationStatus": {
          "stationStatus": "400",
          "stationStatusName": "通讯正常"
        },
        "standbyNum": "0",
        "stationName": "江华白芒营",
        "stationCapacity": "48",
        "longitude": "111.320000000000",
        "interruptNum": "0",
        "maintainNum": "0",
        "dayResources": "9.704545",
        "errorNum": "0",
        "shutdownNum": "1",
        "capabilityRate": "101.515758122235002891",
        "stationPower": "43652",
        "equivalentHours": "1.15852295340104860618",
        "stationUnitCount": "22",
        "provinceName": "湖南省",
        "monthPower": "8189540",
        "noAccessNum": "0",
        "yearPlanRate": "84.844163265306122449"
      },
      {
        "stationCode": 3344131,
        "normalNum": "21",
        "regionName": "吉林",
        "latitude": "44.820000000000",
        "alarmNum": "0",
        "yearPower": "155489548",
        "instantaneous": "11.788571428571428",
        "dayPower": "672817",
        "yearPlanPower": "163520000.0000",
        "stationPlanPower": null,
        "stationStatus": {
          "stationStatus": "400",
          "stationStatusName": "通讯正常"
        },
        "standbyNum": "0",
        "stationName": "通榆乌兰花E",
        "stationCapacity": "48.4",
        "longitude": "123.080000000000",
        "interruptNum": "0",
        "maintainNum": "1",
        "dayResources": "11.788571",
        "errorNum": "0",
        "shutdownNum": "0",
        "capabilityRate": null,
        "stationPower": "12974",
        "equivalentHours": "1.22900900287615514219",
        "stationUnitCount": "22",
        "provinceName": "吉林省",
        "monthPower": "11989007",
        "noAccessNum": "0",
        "yearPlanRate": "95.089009295499021526"
      },
      {
        "stationCode": 3344132,
        "normalNum": "22",
        "regionName": "吉林",
        "latitude": "44.130000000000",
        "alarmNum": "0",
        "yearPower": "94615393",
        "instantaneous": "12.02",
        "dayPower": "695114",
        "yearPlanPower": "152000000.0000",
        "stationPlanPower": null,
        "stationStatus": {
          "stationStatus": "400",
          "stationStatusName": "通讯正常"
        },
        "standbyNum": "0",
        "stationName": "通榆乌兰花D",
        "stationCapacity": "48.4",
        "longitude": "122.200000000000",
        "interruptNum": "0",
        "maintainNum": "0",
        "dayResources": "12.02",
        "errorNum": "0",
        "shutdownNum": "0",
        "capabilityRate": null,
        "stationPower": "15291",
        "equivalentHours": "1.23276374169136236543",
        "stationUnitCount": "22",
        "provinceName": "吉林省",
        "monthPower": "12050144",
        "noAccessNum": "0",
        "yearPlanRate": "62.246969078947368421"
      },
      {
        "stationCode": 3344145,
        "normalNum": "0",
        "regionName": "湖北",
        "latitude": "31.990000000000",
        "alarmNum": null,
        "yearPower": "14838175",
        "instantaneous": null,
        "dayPower": null,
        "yearPlanPower": "90000000.0000",
        "stationPlanPower": null,
        "stationStatus": {
          "stationStatus": "900",
          "stationStatusName": "未接入"
        },
        "standbyNum": "0",
        "stationName": "襄州峪山二期",
        "stationCapacity": "89.5",
        "longitude": "112.370000000000",
        "interruptNum": "32",
        "maintainNum": "0",
        "dayResources": null,
        "errorNum": "0",
        "shutdownNum": "0",
        "capabilityRate": null,
        "stationPower": null,
        "equivalentHours": "1",
        "stationUnitCount": "32",
        "provinceName": "湖北省",
        "monthPower": "1370237",
        "noAccessNum": "0",
        "yearPlanRate": "16.486861111111111111"
      },
      {
        "stationCode": 3344146,
        "normalNum": "0",
        "regionName": "蒙东",
        "latitude": "43.780000000000",
        "alarmNum": null,
        "yearPower": "118924390",
        "instantaneous": null,
        "dayPower": null,
        "yearPlanPower": "100000000.0000",
        "stationPlanPower": null,
        "stationStatus": {
          "stationStatus": "900",
          "stationStatusName": "未接入"
        },
        "standbyNum": "0",
        "stationName": "开鲁建华二期",
        "stationCapacity": "249.9",
        "longitude": "121.400000000000",
        "interruptNum": "70",
        "maintainNum": "0",
        "dayResources": null,
        "errorNum": "0",
        "shutdownNum": "0",
        "capabilityRate": null,
        "stationPower": null,
        "equivalentHours": "1",
        "stationUnitCount": "70",
        "provinceName": "内蒙古自治区",
        "monthPower": "21088200",
        "noAccessNum": "0",
        "yearPlanRate": "118.92439"
      },
      {
        "stationCode": 3344148,
        "normalNum": "0",
        "regionName": "河北",
        "latitude": "41.629080000000",
        "alarmNum": null,
        "yearPower": "20132028",
        "instantaneous": null,
        "dayPower": null,
        "yearPlanPower": "107000000.0000",
        "stationPlanPower": null,
        "stationStatus": {
          "stationStatus": "900",
          "stationStatusName": "未接入"
        },
        "standbyNum": "0",
        "stationName": "康保徐五林",
        "stationCapacity": "48",
        "longitude": "114.296570000000",
        "interruptNum": "24",
        "maintainNum": "0",
        "dayResources": null,
        "errorNum": "0",
        "shutdownNum": "0",
        "capabilityRate": null,
        "stationPower": null,
        "equivalentHours": "1",
        "stationUnitCount": "24",
        "provinceName": "河北省",
        "monthPower": "3984120",
        "noAccessNum": "0",
        "yearPlanRate": "18.814979439252336449"
      },
      {
        "stationCode": 3344178,
        "normalNum": "0",
        "regionName": "蒙东",
        "latitude": "45.131100000000",
        "alarmNum": null,
        "yearPower": "54156586",
        "instantaneous": null,
        "dayPower": null,
        "yearPlanPower": "55000000.0000",
        "stationPlanPower": null,
        "stationStatus": {
          "stationStatus": "900",
          "stationStatusName": "未接入"
        },
        "standbyNum": "0",
        "stationName": "扎旗四期",
        "stationCapacity": "49.5",
        "longitude": "119.541900000000",
        "interruptNum": "33",
        "maintainNum": "0",
        "dayResources": null,
        "errorNum": "0",
        "shutdownNum": "0",
        "capabilityRate": null,
        "stationPower": null,
        "equivalentHours": "1",
        "stationUnitCount": "33",
        "provinceName": "内蒙古自治区",
        "monthPower": "8137080",
        "noAccessNum": "0",
        "yearPlanRate": "98.46652"
      },
      {
        "stationCode": 3344197,
        "normalNum": "0",
        "regionName": "山西",
        "latitude": "39.143000000000",
        "alarmNum": "0",
        "yearPower": "57777498",
        "instantaneous": null,
        "dayPower": null,
        "yearPlanPower": "88000000.0000",
        "stationPlanPower": null,
        "stationStatus": {
          "stationStatus": "900",
          "stationStatusName": "未接入"
        },
        "standbyNum": "0",
        "stationName": "山西繁峙",
        "stationCapacity": "99.95",
        "longitude": "113.174400000000",
        "interruptNum": "33",
        "maintainNum": "0",
        "dayResources": null,
        "errorNum": "0",
        "shutdownNum": "0",
        "capabilityRate": null,
        "stationPower": null,
        "equivalentHours": "1",
        "stationUnitCount": "33",
        "provinceName": "山西省",
        "monthPower": "15304443",
        "noAccessNum": "0",
        "yearPlanRate": "65.656247727272727273"
      },
      {
        "stationCode": 3344198,
        "normalNum": "22",
        "regionName": "吉林",
        "latitude": "44.820000000000",
        "alarmNum": "0",
        "yearPower": "48565998",
        "instantaneous": "13.586086956521738",
        "dayPower": "695242",
        "yearPlanPower": "85000000.0000",
        "stationPlanPower": null,
        "stationStatus": {
          "stationStatus": "400",
          "stationStatusName": "通讯正常"
        },
        "standbyNum": "0",
        "stationName": "通榆乌兰花F",
        "stationCapacity": "48.3",
        "longitude": "123.080000000000",
        "interruptNum": "0",
        "maintainNum": "1",
        "dayResources": "13.586087",
        "errorNum": "0",
        "shutdownNum": "0",
        "capabilityRate": null,
        "stationPower": "48203",
        "equivalentHours": "1.19466386672266554669",
        "stationUnitCount": "23",
        "provinceName": "吉林省",
        "monthPower": "11985787",
        "noAccessNum": "0",
        "yearPlanRate": "57.136468235294117647"
      }
    ],
    "stationDataSummary": {
      "stationStatusSummary": [
        {
          "stationNum": 8,
          "stationStatus": 500,
          "stationStatusName": "通讯中断"
        },
        {
          "stationNum": 31,
          "stationStatus": 900,
          "stationStatusName": "未接入"
        },
        {
          "stationNum": 25,
          "stationStatus": 400,
          "stationStatusName": "通讯正常"
        }
      ],
      "stationProvinceSummary": [
        {
          "provinceCode": "620000",
          "provinceName": "甘肃省",
          "windStationNum": 1
        },
        {
          "provinceCode": "370000",
          "provinceName": "山东省",
          "windStationNum": 1
        },
        {
          "provinceCode": "130000",
          "provinceName": "河北省",
          "windStationNum": 1
        },
        {
          "provinceCode": "210000",
          "provinceName": "辽宁省",
          "windStationNum": 6
        },
        {
          "provinceCode": "530000",
          "provinceName": "云南省",
          "windStationNum": 2
        },
        {
          "provinceCode": "220000",
          "provinceName": "吉林省",
          "windStationNum": 7
        },
        {
          "provinceCode": "420000",
          "provinceName": "湖北省",
          "windStationNum": 6
        },
        {
          "provinceCode": "140000",
          "provinceName": "山西省",
          "windStationNum": 1
        },
        {
          "provinceCode": "410000",
          "provinceName": "河南省",
          "windStationNum": 4
        },
        {
          "provinceCode": "150000",
          "provinceName": "内蒙古自治区",
          "windStationNum": 12
        },
        {
          "provinceCode": "340000",
          "provinceName": "安徽省",
          "windStationNum": 10
        },
        {
          "provinceCode": "450000",
          "provinceName": "广西省",
          "windStationNum": 3
        },
        {
          "provinceCode": "430000",
          "provinceName": "湖南省",
          "windStationNum": 10
        }
      ],
      "maintainNum": "4",
      "monthRate": "64.90941816802941405",
      "normalNum": "505",
      "yearPower": "5441931558.99975277782",
      "alarmNum": "55",
      "errorNum": "6",
      "instantaneous": 9.73267482517482471329,
      "shutdownNum": "2",
      "yearRate": "84.064489782989050437",
      "dayPower": "11778988.44815277782",
      "capabilityRate": "95.421836455441293846",
      "stationPower": "819593.699999999984",
      "stationPlanPower": "814640.27102566893729473",
      "equivalentHours": 4.29805080446668845583,
      "standbyNum": "16",
      "stationUnitCount": "1928",
      "monthPower": "372450241.44815277782",
      "stationCapacity": "3571.5",
      "interruptNum": "1393"
    }
  },
  "message": "查询成功",
  "serviceCode": null
}